{"timestamp": 13.91, "object_list": [{"position": [114.16, 191.68], "velocity": [-0.0, 0.0], "heading": 90.7, "angular velocity": -0.0, "acceleration": [-0.0, 0.0], "light status": {"stopped": 1, "lightID": 5}, "id": 1}, {"position": [106.75, 191.56], "velocity": [-0.0, -0.0], "heading": 90.6, "angular velocity": 0.0, "acceleration": [-0.0, -0.0], "light status": {"stopped": 0, "lightID": 0}, "id": 5}, {"position": [113.89, 187.5], "velocity": [-5.61, 0.15], "heading": 271.6, "angular velocity": -0.84, "acceleration": [-1.11, 0.11], "light status": {"stopped": 0, "lightID": 0}, "id": 23}, {"position": [148.17, 187.58], "velocity": [-5.15, 0.06], "heading": 270.7, "angular velocity": -0.0, "acceleration": [-0.95, 0.01], "light status": {"stopped": 0, "lightID": 0}, "id": 22}, {"position": [99.04, 191.55], "velocity": [0.0, -0.0], "heading": 89.5, "angular velocity": 0.0, "acceleration": [0.0, -0.0], "light status": {"stopped": 0, "lightID": 0}, "id": 18}], "frame": 1110, "size": 5}