{"timestamp": 44.82, "object_list": [{"position": [160.88, 187.52], "velocity": [0.0, 0.0], "heading": 270.4, "angular velocity": 0.0, "acceleration": [-0.0, 0.0], "light status": {"stopped": 0, "lightID": 0}, "id": 2}, {"position": [132.09, 222.14], "velocity": [-0.05, 4.29], "heading": 359.3, "angular velocity": -0.26, "acceleration": [0.02, 1.64], "light status": {"stopped": 0, "lightID": 0}, "id": 1}, {"position": [112.98, 191.52], "velocity": [-0.0, 0.0], "heading": 89.5, "angular velocity": 0.0, "acceleration": [-0.0, 0.0], "light status": {"stopped": 1, "lightID": 5}, "id": 7}, {"position": [136.0, 219.35], "velocity": [0.05, -2.54], "heading": 178.9, "angular velocity": 0.31, "acceleration": [0.08, -1.68], "light status": {"stopped": 0, "lightID": 0}, "id": 15}, {"position": [154.17, 187.35], "velocity": [0.0, -0.0], "heading": 271.2, "angular velocity": -0.0, "acceleration": [0.0, 0.0], "light status": {"stopped": 1, "lightID": 7}, "id": 17}, {"position": [105.77, 191.63], "velocity": [-0.0, -0.0], "heading": 90.0, "angular velocity": 0.0, "acceleration": [0.0, -0.0], "light status": {"stopped": 0, "lightID": 0}, "id": 12}, {"position": [136.06, 206.52], "velocity": [0.01, -3.85], "heading": 179.8, "angular velocity": 0.39, "acceleration": [0.08, -1.33], "light status": {"stopped": 0, "lightID": 0}, "id": 26}, {"position": [161.69, 191.6], "velocity": [4.63, 0.01], "heading": 89.9, "angular velocity": 0.03, "acceleration": [0.47, 0.0], "light status": {"stopped": 0, "lightID": 0}, "id": 18}, {"position": [140.97, 192.35], "velocity": [5.11, -1.34], "heading": 104.7, "angular velocity": 31.37, "acceleration": [0.58, 0.73], "light status": {"stopped": 0, "lightID": 0}, "id": 42}, {"position": [168.28, 187.65], "velocity": [0.0, 0.0], "heading": 268.9, "angular velocity": -0.0, "acceleration": [-0.0, -0.0], "light status": {"stopped": 0, "lightID": 0}, "id": 46}], "frame": 3540, "size": 10}