{"timestamp": 4.92, "object_list": [{"position": [114.16, 191.68], "velocity": [-0.0, 0.0], "heading": 90.7, "angular velocity": 0.0, "acceleration": [0.0, -0.0], "light status": {"stopped": 1, "lightID": 5}, "id": 1}, {"position": [101.73, 191.63], "velocity": [2.65, -0.04], "heading": 91.0, "angular velocity": -0.01, "acceleration": [-6.28, 0.11], "light status": {"stopped": 0, "lightID": 0}, "id": 5}, {"position": [132.09, 226.11], "velocity": [0.03, 6.19], "heading": 0.3, "angular velocity": -0.04, "acceleration": [0.0, -0.55], "light status": {"stopped": 0, "lightID": 0}, "id": 21}, {"position": [136.05, 218.26], "velocity": [0.12, -4.71], "heading": 178.5, "angular velocity": 0.02, "acceleration": [0.06, -2.19], "light status": {"stopped": 0, "lightID": 0}, "id": 23}, {"position": [166.83, 187.55], "velocity": [-5.92, -0.11], "heading": 268.9, "angular velocity": -0.83, "acceleration": [0.02, 0.04], "light status": {"stopped": 0, "lightID": 0}, "id": 22}, {"position": [136.23, 201.09], "velocity": [0.14, -6.38], "heading": 178.8, "angular velocity": -0.35, "acceleration": [0.31, 0.46], "light status": {"stopped": 0, "lightID": 0}, "id": 32}, {"position": [162.84, 191.66], "velocity": [5.97, -0.06], "heading": 90.6, "angular velocity": -0.02, "acceleration": [-0.04, -0.0], "light status": {"stopped": 0, "lightID": 0}, "id": 43}, {"position": [132.09, 209.0], "velocity": [0.05, 5.09], "heading": 0.5, "angular velocity": -0.06, "acceleration": [-0.02, 1.74], "light status": {"stopped": 0, "lightID": 0}, "id": 45}, {"position": [105.61, 187.56], "velocity": [-5.97, -0.15], "heading": 268.5, "angular velocity": -0.66, "acceleration": [0.05, 0.12], "light status": {"stopped": 0, "lightID": 0}, "id": 47}], "frame": 390, "size": 9}