{"timestamp": 461.33, "object_list": [{"position": [132.13, 217.84], "velocity": [-0.0, 0.0], "heading": 0.0, "angular velocity": -0.0, "acceleration": [-0.0, -0.0], "light status": {"stopped": 1, "lightID": 3}, "id": 5}, {"position": [148.84, 187.61], "velocity": [-4.52, 0.03], "heading": 270.4, "angular velocity": -0.0, "acceleration": [-0.08, 0.0], "light status": {"stopped": 0, "lightID": 0}, "id": 4}, {"position": [136.21, 222.37], "velocity": [-0.12, -4.98], "heading": 181.4, "angular velocity": -0.5, "acceleration": [0.04, -0.03], "light status": {"stopped": 0, "lightID": 0}, "id": 29}, {"position": [113.68, 187.57], "velocity": [-5.39, 0.02], "heading": 270.2, "angular velocity": -2.12, "acceleration": [-0.02, -0.0], "light status": {"stopped": 0, "lightID": 0}, "id": 34}, {"position": [163.33, 191.72], "velocity": [0.0, 0.0], "heading": 0.0, "angular velocity": 0.0, "acceleration": [-0.0, 0.0], "light status": {"stopped": 0, "lightID": 0}, "id": 33}, {"position": [131.34, 187.58], "velocity": [-5.32, -0.02], "heading": 269.7, "angular velocity": -1.29, "acceleration": [-0.02, 0.01], "light status": {"stopped": 0, "lightID": 0}, "id": 31}], "frame": 13840, "size": 6}