{"timestamp": 18.07, "object_list": [{"position": [136.03, 210.18], "velocity": [-0.0, 0.0], "heading": 0.0, "angular velocity": -0.0, "acceleration": [-0.0, 0.0], "light status": {"stopped": 1, "lightID": 6}, "id": 2}, {"position": [109.28, 191.65], "velocity": [2.68, -0.01], "heading": 90.1, "angular velocity": -0.1, "acceleration": [2.24, -0.0], "light status": {"stopped": 0, "lightID": 0}, "id": 15}, {"position": [125.21, 191.66], "velocity": [4.83, 0.02], "heading": 89.8, "angular velocity": -0.21, "acceleration": [0.05, -0.02], "light status": {"stopped": 0, "lightID": 0}, "id": 14}, {"position": [132.25, 218.73], "velocity": [0.0, -0.0], "heading": 0.0, "angular velocity": -0.0, "acceleration": [0.0, 0.0], "light status": {"stopped": 1, "lightID": 3}, "id": 39}, {"position": [165.81, 191.6], "velocity": [-0.0, 0.0], "heading": 0.0, "angular velocity": -0.0, "acceleration": [0.0, 0.0], "light status": {"stopped": 0, "lightID": 0}, "id": 30}], "frame": 542, "size": 5}