{"timestamp": 241.73, "object_list": [{"position": [166.7, 191.67], "velocity": [2.2, -0.0], "heading": 90.0, "angular velocity": -0.03, "acceleration": [-6.02, -0.01], "light status": {"stopped": 0, "lightID": 0}, "id": 15}, {"position": [161.61, 187.72], "velocity": [0.0, 0.0], "heading": 0.0, "angular velocity": 0.0, "acceleration": [-0.0, -0.0], "light status": {"stopped": 0, "lightID": 0}, "id": 14}, {"position": [136.16, 215.3], "velocity": [-0.05, -2.7], "heading": 181.0, "angular velocity": 0.01, "acceleration": [0.12, 6.31], "light status": {"stopped": 0, "lightID": 0}, "id": 38}, {"position": [136.0, 204.44], "velocity": [0.04, -4.42], "heading": 179.4, "angular velocity": 0.74, "acceleration": [-0.08, -1.87], "light status": {"stopped": 0, "lightID": 0}, "id": 10}, {"position": [153.36, 187.69], "velocity": [0.0, 0.0], "heading": 0.0, "angular velocity": -0.0, "acceleration": [0.0, -0.0], "light status": {"stopped": 1, "lightID": 7}, "id": 33}, {"position": [156.69, 191.66], "velocity": [0.25, -0.0], "heading": 0.0, "angular velocity": -0.0, "acceleration": [-0.0, -0.0], "light status": {"stopped": 0, "lightID": 0}, "id": 19}], "frame": 7252, "size": 6}