{"timestamp": 274.33, "object_list": [{"position": [162.85, 187.56], "velocity": [-0.0, -0.0], "heading": 0.0, "angular velocity": -0.0, "acceleration": [-0.0, 0.0], "light status": {"stopped": 0, "lightID": 0}, "id": 39}, {"position": [154.27, 187.55], "velocity": [-0.0, -0.0], "heading": 0.0, "angular velocity": -0.0, "acceleration": [-0.0, -0.0], "light status": {"stopped": 1, "lightID": 7}, "id": 20}, {"position": [137.32, 194.09], "velocity": [2.99, -3.77], "heading": 141.6, "angular velocity": 37.75, "acceleration": [3.35, 2.33], "light status": {"stopped": 0, "lightID": 0}, "id": 37}, {"position": [132.2, 217.83], "velocity": [0.01, 2.49], "heading": 0.1, "angular velocity": 0.36, "acceleration": [-0.05, 2.03], "light status": {"stopped": 0, "lightID": 0}, "id": 33}], "frame": 8230, "size": 4}