{"timestamp": 415.0, "object_list": [{"position": [164.41, 187.56], "velocity": [-5.25, -0.13], "heading": 268.6, "angular velocity": -2.98, "acceleration": [-0.02, 0.08], "light status": {"stopped": 0, "lightID": 0}, "id": 12}, {"position": [151.84, 191.64], "velocity": [2.36, 0.01], "heading": 89.7, "angular velocity": -0.04, "acceleration": [2.11, 0.01], "light status": {"stopped": 0, "lightID": 0}, "id": 38}, {"position": [165.28, 191.72], "velocity": [0.0, 0.0], "heading": 0.0, "angular velocity": 0.0, "acceleration": [-0.0, 0.0], "light status": {"stopped": 0, "lightID": 0}, "id": 22}], "frame": 12450, "size": 3}