{"timestamp": 602.67, "object_list": [{"position": [98.93, 191.64], "velocity": [2.75, -0.03], "heading": 90.6, "angular velocity": -0.29, "acceleration": [-15.5, 0.11], "light status": {"stopped": 0, "lightID": 0}, "id": 15}, {"position": [132.06, 218.86], "velocity": [-0.0, -0.0], "heading": 0.0, "angular velocity": 0.0, "acceleration": [0.0, 0.0], "light status": {"stopped": 1, "lightID": 3}, "id": 29}, {"position": [113.29, 191.63], "velocity": [0.0, -0.0], "heading": 0.0, "angular velocity": 0.0, "acceleration": [0.0, -0.0], "light status": {"stopped": 1, "lightID": 5}, "id": 13}, {"position": [153.42, 187.75], "velocity": [-0.95, -0.01], "heading": 0.0, "angular velocity": -0.05, "acceleration": [-3.09, -0.05], "light status": {"stopped": 0, "lightID": 0}, "id": 19}], "frame": 18080, "size": 4}