{"timestamp": 367.0, "object_list": [{"position": [168.18, 187.67], "velocity": [-0.0, 0.0], "heading": 0.0, "angular velocity": 0.0, "acceleration": [-0.0, 0.0], "light status": {"stopped": 0, "lightID": 0}, "id": 1}, {"position": [157.45, 191.65], "velocity": [4.83, 0.12], "heading": 88.6, "angular velocity": 0.05, "acceleration": [0.04, -0.04], "light status": {"stopped": 0, "lightID": 0}, "id": 16}, {"position": [161.97, 187.61], "velocity": [0.0, 0.0], "heading": 0.0, "angular velocity": 0.0, "acceleration": [0.0, 0.0], "light status": {"stopped": 0, "lightID": 0}, "id": 26}, {"position": [154.46, 187.77], "velocity": [-0.0, 0.0], "heading": 0.0, "angular velocity": 0.0, "acceleration": [0.0, 0.0], "light status": {"stopped": 1, "lightID": 7}, "id": 18}], "frame": 11010, "size": 4}