{"timestamp": 376.0, "object_list": [{"position": [155.43, 187.55], "velocity": [-4.48, -0.0], "heading": 270.0, "angular velocity": -0.37, "acceleration": [0.06, 0.01], "light status": {"stopped": 0, "lightID": 0}, "id": 1}, {"position": [165.17, 187.6], "velocity": [-2.24, -0.03], "heading": 269.2, "angular velocity": -0.17, "acceleration": [-0.41, 0.0], "light status": {"stopped": 0, "lightID": 0}, "id": 35}, {"position": [113.26, 191.7], "velocity": [-0.0, -0.0], "heading": 0.0, "angular velocity": 0.0, "acceleration": [-0.0, -0.0], "light status": {"stopped": 1, "lightID": 5}, "id": 23}, {"position": [139.78, 187.58], "velocity": [-5.19, 0.01], "heading": 270.2, "angular velocity": 1.97, "acceleration": [-0.02, -0.0], "light status": {"stopped": 0, "lightID": 0}, "id": 26}, {"position": [131.94, 202.68], "velocity": [-0.01, 5.21], "heading": 359.9, "angular velocity": -6.59, "acceleration": [0.13, 0.01], "light status": {"stopped": 0, "lightID": 0}, "id": 18}], "frame": 11280, "size": 5}