{"timestamp": 405.33, "object_list": [{"position": [136.21, 206.22], "velocity": [0.03, -4.37], "heading": 179.6, "angular velocity": -0.42, "acceleration": [-0.0, -2.1], "light status": {"stopped": 0, "lightID": 0}, "id": 2}, {"position": [139.78, 192.21], "velocity": [4.5, -0.93], "heading": 101.7, "angular velocity": 46.92, "acceleration": [0.76, 0.33], "light status": {"stopped": 0, "lightID": 0}, "id": 6}, {"position": [161.7, 187.49], "velocity": [0.0, 0.0], "heading": 0.0, "angular velocity": 0.0, "acceleration": [0.0, 0.0], "light status": {"stopped": 0, "lightID": 0}, "id": 38}, {"position": [168.38, 187.68], "velocity": [0.0, -0.0], "heading": 0.0, "angular velocity": -0.0, "acceleration": [-0.0, 0.0], "light status": {"stopped": 0, "lightID": 0}, "id": 11}, {"position": [154.06, 187.55], "velocity": [0.0, 0.0], "heading": 0.0, "angular velocity": 0.0, "acceleration": [0.0, 0.0], "light status": {"stopped": 1, "lightID": 7}, "id": 35}, {"position": [157.06, 191.65], "velocity": [2.76, 0.06], "heading": 88.8, "angular velocity": -0.26, "acceleration": [1.61, 0.01], "light status": {"stopped": 0, "lightID": 0}, "id": 22}, {"position": [113.5, 191.57], "velocity": [0.0, 0.0], "heading": 0.0, "angular velocity": -0.0, "acceleration": [0.0, 0.0], "light status": {"stopped": 1, "lightID": 5}, "id": 27}, {"position": [136.0, 219.91], "velocity": [0.06, -3.02], "heading": 178.9, "angular velocity": 0.39, "acceleration": [-0.0, -2.35], "light status": {"stopped": 0, "lightID": 0}, "id": 9}], "frame": 12160, "size": 8}