{"timestamp": 481.0, "object_list": [{"position": [132.13, 218.0], "velocity": [-0.02, 1.34], "heading": 359.2, "angular velocity": -0.02, "acceleration": [-0.08, 5.32], "light status": {"stopped": 0, "lightID": 0}, "id": 5}, {"position": [136.01, 209.15], "velocity": [0.0, -0.21], "heading": 0.0, "angular velocity": 0.03, "acceleration": [0.04, -3.47], "light status": {"stopped": 0, "lightID": 0}, "id": 29}, {"position": [163.33, 191.72], "velocity": [-0.0, 0.0], "heading": 0.0, "angular velocity": 0.0, "acceleration": [-0.0, -0.0], "light status": {"stopped": 0, "lightID": 0}, "id": 33}, {"position": [136.04, 216.85], "velocity": [0.0, 0.0], "heading": 0.0, "angular velocity": -0.0, "acceleration": [0.0, 0.0], "light status": {"stopped": 0, "lightID": 0}, "id": 30}], "frame": 14430, "size": 4}