{"timestamp": 618.67, "object_list": [{"position": [160.99, 187.56], "velocity": [0.0, 0.0], "heading": 0.0, "angular velocity": -0.0, "acceleration": [0.0, 0.0], "light status": {"stopped": 0, "lightID": 0}, "id": 7}, {"position": [119.52, 187.49], "velocity": [-4.92, 0.11], "heading": 271.2, "angular velocity": -1.29, "acceleration": [-0.03, 0.06], "light status": {"stopped": 0, "lightID": 0}, "id": 16}, {"position": [134.86, 192.48], "velocity": [-2.55, -4.33], "heading": 210.5, "angular velocity": -32.78, "acceleration": [-3.62, 2.17], "light status": {"stopped": 0, "lightID": 0}, "id": 34}, {"position": [166.61, 191.71], "velocity": [2.99, 0.01], "heading": 89.8, "angular velocity": -0.38, "acceleration": [-8.34, -0.08], "light status": {"stopped": 0, "lightID": 0}, "id": 37}, {"position": [153.46, 187.68], "velocity": [0.0, -0.0], "heading": 0.0, "angular velocity": -0.0, "acceleration": [0.0, -0.0], "light status": {"stopped": 1, "lightID": 7}, "id": 32}], "frame": 18560, "size": 5}