{"timestamp": 130.33, "object_list": [{"position": [165.64, 187.72], "velocity": [-2.71, 0.01], "heading": 270.2, "angular velocity": 0.67, "acceleration": [4.72, -0.17], "light status": {"stopped": 0, "lightID": 0}, "id": 3}, {"position": [153.46, 187.72], "velocity": [0.0, 0.0], "heading": 0.0, "angular velocity": -0.0, "acceleration": [0.0, -0.0], "light status": {"stopped": 1, "lightID": 7}, "id": 0}, {"position": [113.61, 191.57], "velocity": [1.54, 0.03], "heading": 89.0, "angular velocity": 0.0, "acceleration": [3.42, 0.06], "light status": {"stopped": 0, "lightID": 0}, "id": 14}, {"position": [99.81, 191.59], "velocity": [0.0, -0.0], "heading": 0.0, "angular velocity": 0.0, "acceleration": [0.0, -0.0], "light status": {"stopped": 0, "lightID": 0}, "id": 17}, {"position": [106.91, 191.62], "velocity": [-0.0, -0.0], "heading": 0.0, "angular velocity": -0.0, "acceleration": [-0.0, -0.0], "light status": {"stopped": 0, "lightID": 0}, "id": 26}], "frame": 3910, "size": 5}