{"timestamp": 256.33, "object_list": [{"position": [132.24, 219.21], "velocity": [-0.0, -0.0], "heading": 0.0, "angular velocity": -0.0, "acceleration": [0.0, -0.0], "light status": {"stopped": 1, "lightID": 3}, "id": 4}, {"position": [163.95, 187.57], "velocity": [-2.94, -0.02], "heading": 269.6, "angular velocity": -0.37, "acceleration": [-2.73, -0.02], "light status": {"stopped": 0, "lightID": 0}, "id": 39}, {"position": [154.27, 187.55], "velocity": [0.0, 0.0], "heading": 0.0, "angular velocity": 0.0, "acceleration": [-0.0, 0.0], "light status": {"stopped": 1, "lightID": 7}, "id": 20}, {"position": [109.33, 187.64], "velocity": [-4.8, 0.0], "heading": 270.0, "angular velocity": 0.09, "acceleration": [-0.04, -0.01], "light status": {"stopped": 0, "lightID": 0}, "id": 22}, {"position": [132.07, 197.62], "velocity": [-0.16, 4.79], "heading": 358.1, "angular velocity": -14.01, "acceleration": [0.53, 0.03], "light status": {"stopped": 0, "lightID": 0}, "id": 33}, {"position": [113.62, 191.71], "velocity": [0.03, -0.0], "heading": 0.0, "angular velocity": 0.55, "acceleration": [0.56, -0.02], "light status": {"stopped": 0, "lightID": 0}, "id": 30}], "frame": 7690, "size": 6}