{"timestamp": 75.67, "object_list": [{"position": [136.15, 209.63], "velocity": [-0.0, 0.0], "heading": 179.2, "angular velocity": -0.0, "acceleration": [0.0, -0.0], "light status": {"stopped": 1, "lightID": 6}, "id": 3}, {"position": [114.37, 191.62], "velocity": [-0.0, -0.0], "heading": 89.9, "angular velocity": -0.0, "acceleration": [-0.0, 0.0], "light status": {"stopped": 1, "lightID": 5}, "id": 1}, {"position": [109.92, 187.56], "velocity": [-5.42, 0.11], "heading": 271.2, "angular velocity": 1.43, "acceleration": [-0.02, 0.03], "light status": {"stopped": 0, "lightID": 0}, "id": 5}, {"position": [129.09, 187.86], "velocity": [-5.14, -0.94], "heading": 259.6, "angular velocity": -27.97, "acceleration": [-0.44, 0.93], "light status": {"stopped": 0, "lightID": 0}, "id": 7}, {"position": [153.94, 187.54], "velocity": [-0.0, 0.0], "heading": 270.6, "angular velocity": -0.0, "acceleration": [-0.0, 0.0], "light status": {"stopped": 1, "lightID": 7}, "id": 13}, {"position": [161.85, 187.55], "velocity": [-0.0, -0.0], "heading": 269.4, "angular velocity": -0.0, "acceleration": [-0.0, -0.0], "light status": {"stopped": 0, "lightID": 0}, "id": 19}], "frame": 2270, "size": 6}