{"timestamp": 43.33, "object_list": [{"position": [117.86, 187.6], "velocity": [-4.86, -0.02], "heading": 269.8, "angular velocity": -0.02, "acceleration": [-0.04, 0.0], "light status": {"stopped": 0, "lightID": 0}, "id": 2}, {"position": [112.75, 191.61], "velocity": [-0.0, 0.0], "heading": 0.0, "angular velocity": 0.0, "acceleration": [0.0, -0.0], "light status": {"stopped": 1, "lightID": 5}, "id": 39}, {"position": [135.58, 189.46], "velocity": [-3.38, 3.23], "heading": 313.7, "angular velocity": -33.22, "acceleration": [1.26, 1.58], "light status": {"stopped": 0, "lightID": 0}, "id": 32}, {"position": [99.4, 187.61], "velocity": [-5.34, 0.02], "heading": 270.2, "angular velocity": 0.04, "acceleration": [-0.02, -0.01], "light status": {"stopped": 0, "lightID": 0}, "id": 25}, {"position": [105.61, 191.57], "velocity": [0.0, -0.0], "heading": 0.0, "angular velocity": 0.0, "acceleration": [0.0, -0.0], "light status": {"stopped": 0, "lightID": 0}, "id": 30}, {"position": [136.09, 210.28], "velocity": [0.0, 0.0], "heading": 0.0, "angular velocity": -0.0, "acceleration": [0.0, -0.0], "light status": {"stopped": 1, "lightID": 6}, "id": 18}], "frame": 1300, "size": 6}