{"timestamp": 382.67, "object_list": [{"position": [132.29, 208.52], "velocity": [-0.03, 1.65], "heading": 359.1, "angular velocity": 0.29, "acceleration": [-0.06, 3.03], "light status": {"stopped": 0, "lightID": 0}, "id": 1}, {"position": [151.96, 191.61], "velocity": [2.57, 0.01], "heading": 89.7, "angular velocity": 0.04, "acceleration": [3.19, 0.02], "light status": {"stopped": 0, "lightID": 0}, "id": 28}, {"position": [161.28, 191.63], "velocity": [1.97, 0.03], "heading": 89.2, "angular velocity": -0.09, "acceleration": [-5.74, -0.1], "light status": {"stopped": 0, "lightID": 0}, "id": 17}, {"position": [135.98, 221.29], "velocity": [0.02, -2.59], "heading": 179.5, "angular velocity": 0.9, "acceleration": [0.01, -3.34], "light status": {"stopped": 0, "lightID": 0}, "id": 20}, {"position": [136.22, 207.81], "velocity": [0.02, -4.69], "heading": 179.7, "angular velocity": -0.67, "acceleration": [-0.06, 0.24], "light status": {"stopped": 0, "lightID": 0}, "id": 22}, {"position": [132.05, 222.56], "velocity": [-0.0, 4.7], "heading": 360.0, "angular velocity": -0.53, "acceleration": [0.04, -0.21], "light status": {"stopped": 0, "lightID": 0}, "id": 26}, {"position": [134.56, 191.97], "velocity": [-3.06, -4.19], "heading": 216.1, "angular velocity": -29.32, "acceleration": [-1.18, -0.21], "light status": {"stopped": 0, "lightID": 0}, "id": 31}], "frame": 11480, "size": 7}