{"timestamp": 27.57, "object_list": [{"position": [132.32, 204.48], "velocity": [0.0, -0.0], "heading": 0.0, "angular velocity": -0.0, "acceleration": [-0.0, -0.0], "light status": {"stopped": 0, "lightID": 0}, "id": 15}, {"position": [143.61, 191.62], "velocity": [4.68, -0.01], "heading": 90.1, "angular velocity": -0.0, "acceleration": [0.04, -0.0], "light status": {"stopped": 0, "lightID": 0}, "id": 28}, {"position": [136.0, 218.77], "velocity": [0.16, -4.86], "heading": 178.1, "angular velocity": 0.61, "acceleration": [0.11, -0.03], "light status": {"stopped": 0, "lightID": 0}, "id": 13}, {"position": [154.17, 187.46], "velocity": [-0.86, 0.0], "heading": 0.0, "angular velocity": 0.09, "acceleration": [16.54, -0.33], "light status": {"stopped": 1, "lightID": 7}, "id": 35}, {"position": [132.11, 211.99], "velocity": [-0.0, -0.0], "heading": 0.0, "angular velocity": -0.0, "acceleration": [-0.0, 0.0], "light status": {"stopped": 0, "lightID": 0}, "id": 22}, {"position": [132.06, 218.8], "velocity": [0.0, -0.0], "heading": 0.0, "angular velocity": 0.0, "acceleration": [0.0, -0.0], "light status": {"stopped": 1, "lightID": 3}, "id": 27}], "frame": 827, "size": 6}