{"timestamp": 80.33, "object_list": [{"position": [132.23, 211.14], "velocity": [0.0, -0.0], "heading": 0.0, "angular velocity": -0.0, "acceleration": [0.0, -0.0], "light status": {"stopped": 0, "lightID": 0}, "id": 3}, {"position": [132.23, 218.79], "velocity": [0.0, -0.0], "heading": 0.0, "angular velocity": -0.0, "acceleration": [0.0, 0.0], "light status": {"stopped": 1, "lightID": 3}, "id": 5}, {"position": [132.25, 199.36], "velocity": [0.05, 1.94], "heading": 1.3, "angular velocity": 5.75, "acceleration": [-0.42, -3.65], "light status": {"stopped": 0, "lightID": 0}, "id": 14}], "frame": 2410, "size": 3}