{"timestamp": 81.0, "object_list": [{"position": [132.23, 211.14], "velocity": [0.0, -0.0], "heading": 0.0, "angular velocity": 0.0, "acceleration": [-0.0, 0.0], "light status": {"stopped": 0, "lightID": 0}, "id": 3}, {"position": [132.23, 218.79], "velocity": [-0.0, 0.0], "heading": 0.0, "angular velocity": 0.0, "acceleration": [-0.0, 0.0], "light status": {"stopped": 1, "lightID": 3}, "id": 5}, {"position": [132.31, 200.9], "velocity": [0.01, 3.01], "heading": 0.1, "angular velocity": 5.61, "acceleration": [-0.52, 2.21], "light status": {"stopped": 0, "lightID": 0}, "id": 14}], "frame": 2430, "size": 3}