{"timestamp": 88.33, "object_list": [{"position": [132.03, 222.6], "velocity": [0.01, 4.85], "heading": 0.1, "angular velocity": -0.98, "acceleration": [0.11, -0.34], "light status": {"stopped": 0, "lightID": 0}, "id": 3}, {"position": [132.23, 209.07], "velocity": [-0.05, 2.59], "heading": 358.9, "angular velocity": 0.1, "acceleration": [-0.02, 2.42], "light status": {"stopped": 0, "lightID": 0}, "id": 14}, {"position": [153.43, 187.43], "velocity": [0.0, 0.0], "heading": 0.0, "angular velocity": -0.0, "acceleration": [0.0, 0.0], "light status": {"stopped": 1, "lightID": 7}, "id": 8}], "frame": 2650, "size": 3}