{"timestamp": 378.07, "object_list": [{"position": [153.95, 187.77], "velocity": [-0.0, 0.0], "heading": 0.0, "angular velocity": 0.0, "acceleration": [0.0, -0.0], "light status": {"stopped": 1, "lightID": 7}, "id": 16}, {"position": [124.2, 187.45], "velocity": [-4.92, -0.01], "heading": 269.9, "angular velocity": -7.27, "acceleration": [0.0, 0.58], "light status": {"stopped": 0, "lightID": 0}, "id": 34}, {"position": [136.41, 195.81], "velocity": [0.9, -4.91], "heading": 169.6, "angular velocity": 17.93, "acceleration": [4.1, 0.92], "light status": {"stopped": 0, "lightID": 0}, "id": 26}, {"position": [161.91, 187.72], "velocity": [0.0, -0.0], "heading": 0.0, "angular velocity": 0.0, "acceleration": [0.0, 0.0], "light status": {"stopped": 0, "lightID": 0}, "id": 33}, {"position": [105.33, 187.7], "velocity": [-5.33, 0.09], "heading": 271.0, "angular velocity": 0.68, "acceleration": [0.09, -0.14], "light status": {"stopped": 0, "lightID": 0}, "id": 25}], "frame": 11342, "size": 5}