{"timestamp": 53.2, "object_list": [{"position": [98.68, 191.73], "velocity": [1.38, -0.02], "heading": 90.7, "angular velocity": -0.35, "acceleration": [3.71, -0.05], "light status": {"stopped": 0, "lightID": 0}, "id": 34}, {"position": [132.0, 209.63], "velocity": [0.09, 5.24], "heading": 1.0, "angular velocity": -0.34, "acceleration": [0.03, 0.02], "light status": {"stopped": 0, "lightID": 0}, "id": 35}, {"position": [133.95, 191.24], "velocity": [-2.57, 4.07], "heading": 327.7, "angular velocity": -31.53, "acceleration": [3.78, 2.14], "light status": {"stopped": 0, "lightID": 0}, "id": 30}, {"position": [112.96, 191.61], "velocity": [-0.0, -0.0], "heading": 0.0, "angular velocity": 0.0, "acceleration": [-0.0, -0.0], "light status": {"stopped": 1, "lightID": 5}, "id": 8}], "frame": 1596, "size": 4}