{"timestamp": 584.5, "object_list": [{"position": [126.36, 187.52], "velocity": [-4.96, -0.18], "heading": 268.0, "angular velocity": -12.82, "acceleration": [0.02, -0.83], "light status": {"stopped": 0, "lightID": 0}, "id": 3}, {"position": [132.05, 222.82], "velocity": [0.0, 2.84], "heading": 0.0, "angular velocity": -0.29, "acceleration": [0.0, -3.43], "light status": {"stopped": 0, "lightID": 0}, "id": 6}, {"position": [161.04, 187.55], "velocity": [-0.0, -0.0], "heading": 0.0, "angular velocity": -0.0, "acceleration": [-0.0, -0.0], "light status": {"stopped": 0, "lightID": 0}, "id": 15}, {"position": [153.82, 187.68], "velocity": [-0.0, -0.0], "heading": 0.0, "angular velocity": -0.0, "acceleration": [-0.0, -0.0], "light status": {"stopped": 1, "lightID": 7}, "id": 29}, {"position": [169.09, 187.64], "velocity": [-0.0, -0.0], "heading": 0.0, "angular velocity": 0.0, "acceleration": [-0.0, -0.0], "light status": {"stopped": 0, "lightID": 0}, "id": 32}, {"position": [132.21, 211.52], "velocity": [-0.06, 3.06], "heading": 358.9, "angular velocity": -0.02, "acceleration": [0.05, -1.65], "light status": {"stopped": 0, "lightID": 0}, "id": 30}], "frame": 17535, "size": 6}