{"timestamp": 185.33, "object_list": [{"position": [154.73, 187.69], "velocity": [-4.32, -0.04], "heading": 269.5, "angular velocity": -0.06, "acceleration": [6.87, 0.05], "light status": {"stopped": 0, "lightID": 0}, "id": 3}, {"position": [113.67, 191.64], "velocity": [0.0, 0.0], "heading": 0.0, "angular velocity": -0.0, "acceleration": [-0.0, 0.0], "light status": {"stopped": 1, "lightID": 5}, "id": 28}, {"position": [138.58, 187.55], "velocity": [-5.08, -0.04], "heading": 269.6, "angular velocity": 0.3, "acceleration": [-0.58, 0.05], "light status": {"stopped": 0, "lightID": 0}, "id": 17}, {"position": [132.04, 218.58], "velocity": [0.0, -0.0], "heading": 0.0, "angular velocity": 0.0, "acceleration": [0.0, -0.0], "light status": {"stopped": 1, "lightID": 3}, "id": 34}, {"position": [166.54, 187.64], "velocity": [-2.4, 0.03], "heading": 270.8, "angular velocity": 0.08, "acceleration": [-2.31, 0.03], "light status": {"stopped": 0, "lightID": 0}, "id": 19}], "frame": 5560, "size": 5}