{"timestamp": 223.67, "object_list": [{"position": [112.51, 191.62], "velocity": [0.0, 0.0], "heading": 0.0, "angular velocity": -0.0, "acceleration": [0.0, 0.0], "light status": {"stopped": 1, "lightID": 5}, "id": 2}, {"position": [105.5, 191.59], "velocity": [-0.0, 0.0], "heading": 0.0, "angular velocity": -0.0, "acceleration": [-0.0, 0.0], "light status": {"stopped": 0, "lightID": 0}, "id": 29}, {"position": [132.08, 218.73], "velocity": [-0.0, -0.0], "heading": 0.0, "angular velocity": -0.0, "acceleration": [0.0, -0.0], "light status": {"stopped": 1, "lightID": 3}, "id": 28}, {"position": [164.54, 187.6], "velocity": [-0.0, 0.0], "heading": 0.0, "angular velocity": -0.0, "acceleration": [-0.0, 0.0], "light status": {"stopped": 0, "lightID": 0}, "id": 21}, {"position": [155.31, 187.57], "velocity": [-0.49, 0.0], "heading": 0.0, "angular velocity": -0.67, "acceleration": [-2.67, 0.03], "light status": {"stopped": 0, "lightID": 0}, "id": 23}, {"position": [132.25, 209.48], "velocity": [-0.05, 2.7], "heading": 358.9, "angular velocity": 0.22, "acceleration": [0.0, 2.38], "light status": {"stopped": 0, "lightID": 0}, "id": 36}, {"position": [161.91, 191.72], "velocity": [1.71, 0.0], "heading": 90.0, "angular velocity": -0.37, "acceleration": [1.36, 0.04], "light status": {"stopped": 0, "lightID": 0}, "id": 22}, {"position": [98.33, 191.55], "velocity": [-0.0, -0.0], "heading": 0.0, "angular velocity": -0.0, "acceleration": [0.0, -0.0], "light status": {"stopped": 0, "lightID": 0}, "id": 32}], "frame": 6710, "size": 8}